src/__init__.py
src/main/__init__.py
src/main/cmd.py
src/main/swbs.py
src/main/playbook/bootstrap.yaml
src/main/playbook/roles/agent/tasks/main.yaml
src/main/playbook/roles/controller/tasks/main.yaml
src/main/playbook/roles/meta/main.yaml
src/main/playbook/roles/minio/tasks/main.yaml
src/main/playbook/roles/mysql/tasks/main.yaml
swbootstrap-0.0.23.dist-info/LICENSE
swbootstrap-0.0.23.dist-info/METADATA
swbootstrap-0.0.23.dist-info/WHEEL
swbootstrap-0.0.23.dist-info/entry_points.txt
swbootstrap-0.0.23.dist-info/top_level.txt
swbootstrap-0.0.23.dist-info/RECORD
