Metadata-Version: 2.1
Name: swbootstrap
Version: 0.0.23
Summary: UNKNOWN
Home-page: UNKNOWN
Author: sw
Author-email: 15031259256@163.com
License: UNKNOWN
Platform: UNKNOWN
Classifier: Programming Language :: Python :: 3
Classifier: License :: Free for non-commercial use
Classifier: Operating System :: OS Independent
License-File: LICENSE
Requires-Dist: click
Requires-Dist: ansible-runner
Requires-Dist: ansible
